pixel_perfect/__init__.py
pixel_perfect/actual_screenshots.py
pixel_perfect/baseline_screenshots.py
pixel_perfect/image_comparer.py
pixel_perfect/utils.py
pixel_perfect_package_etsystems/__init__.py
pixel_perfect_package_etsystems/image_comparer.py
pixel_perfect-3.4.3.dist-info/LICENSE.txt
pixel_perfect-3.4.3.dist-info/METADATA
pixel_perfect-3.4.3.dist-info/WHEEL
pixel_perfect-3.4.3.dist-info/top_level.txt
pixel_perfect-3.4.3.dist-info/RECORD
