Metadata-Version: 2.1
Name: pixel-perfect
Version: 3.4.3
Summary: A versatile Python package leveraging machine learning model for efficient image comparisons.
Author: Etenrnal Tech Systems
License-File: LICENSE.txt
Requires-Dist: numpy
Requires-Dist: tensorflow
Requires-Dist: opencv-python
Requires-Dist: selenium
Requires-Dist: Pillow
